nx_yaml/README.md
nx_yaml/__init__.py
nx_yaml/scanner.py
nx_yaml/serializer.py
nx_yaml-1.0.0.dist-info/METADATA
nx_yaml-1.0.0.dist-info/WHEEL
nx_yaml-1.0.0.dist-info/licenses/LICENSE
nx_yaml-1.0.0.dist-info/RECORD
