Metadata-Version: 2.4
Name: nx_yaml
Version: 1.0.0
Summary: YAML as a human-readable Hypergraph Interchange Format (HIF) for NetworkX
Project-URL: Source, https://github.com/colltoaction/nx_yaml
License-File: LICENSE
Requires-Dist: nx-hif==0.0.11
Requires-Dist: pyyaml
